yiki/__init__.py
yiki-0.1.0.dist-info/licenses/LICENSE
yiki-0.1.0.dist-info/METADATA
yiki-0.1.0.dist-info/WHEEL
yiki-0.1.0.dist-info/top_level.txt
yiki-0.1.0.dist-info/RECORD
