Metadata-Version: 2.4
Name: yiki
Version: 0.1.0
Summary: yiki my own tool kit
Author-email: yiki <admin@yiki.io>
License: MIT
Requires-Python: >=3.8
License-File: LICENSE
Dynamic: license-file
